{
  "entityId": "ACKNOWLEDGEMENT",
  "displayName": "✅ Acknowledgement",
  "values": [
    {
      "name": "ok",
      "synonyms": [
        "ok",
        "o. k.",
        "O. K.",
        "okay",
        "o k and",
        "ok and"
      ],
      "__typename": "EntityValue"
    },
    {
      "name": "gotcha",
      "synonyms": [
        "gotcha",
        "got it"
      ],
      "__typename": "EntityValue"
    },
    {
      "name": "sweet",
      "synonyms": [
        "sweet",
        "cool"
      ],
      "__typename": "EntityValue"
    }
  ],
  "__typename": "Entity"
}